lab2/MUX4to1.v
module mux2 (input wire i0, i1, j, output wire o);
  assign o = (j==0)?i0:i1;
endmodule

module mux4 (input wire [0:3] i, input wire j1, j0, output wire o);
  wire  t0, t1;
  
	mux2 m1(i[0], i[1], j0, t0);
	mux2 m2(i[2], i[3], j0, t1);

	mux2 m3(t0, t1, j1, o);

endmodule

lab3/testBench2to1.v
module TB;
reg A,B,S;
wire X;
initial
begin
$dumpfile("dump2.vcd");
$dumpvars(0,TB);
end
mux2 newMUX(.i0(A), .i1(B), .j(S), .o(X));
initial
begin
S = 1'b0;
A = 1'b0;
B = 1'b0;
#5
A = 1'b0;
B = 1'b1;
#5
A = 1'b1;
B = 1'b0;
#5
A = 1'b1;
B = 1'b1;
#5
S = 1'b0;
A = 1'b0;
B = 1'b0;
#5
A = 1'b0;
B = 1'b1;
#5
A = 1'b1;
B = 1'b0;
#5
A = 1'b1;
B = 1'b1;
end
endmodule

lab3/dump2.vcd
$date
	Wed Sep  8 10:04:48 2021
$end
$version
	Icarus Verilog
$end
$timescale
	1s
$end
$scope module TB $end
$var wire 1 ! X $end
$var reg 1 " A $end
$var reg 1 # B $end
$var reg 1 $ S $end
$scope module newMUX $end
$var wire 1 % i0 $end
$var wire 1 & i1 $end
$var wire 1 ' j $end
$var wire 1 ! o $end
$upscope $end
$upscope $end
$enddefinitions $end
#0
$dumpvars
0'
0&
0%
0$
0#
0"
0!
$end
#5
1#
1&
#10
1!
0#
0&
1"
1%
#15
1#
1&
#20
0!
0#
0&
0"
0%
#25
1#
1&
#30
1!
0#
0&
1"
1%
#35
1#
1&
